pyneng_cli/__init__.py
pyneng_cli/exceptions.py
pyneng_cli/pyneng.py
pyneng_cli/pyneng_docs.py
pyneng_cli/utils.py
pyneng_cli-5.1.0.dist-info/LICENSE
pyneng_cli-5.1.0.dist-info/METADATA
pyneng_cli-5.1.0.dist-info/WHEEL
pyneng_cli-5.1.0.dist-info/entry_points.txt
pyneng_cli-5.1.0.dist-info/top_level.txt
pyneng_cli-5.1.0.dist-info/RECORD
