Metadata-Version: 2.1
Name: pyneng-cli
Version: 5.1.0
Summary: CLI tool for testing tasks from the book Python for Network Engineers
Home-page: https://github.com/natenka/pyneng-cli
Author: Natasha Samoylenko
Author-email: "Natasha Samoylenko" <natasha.samoylenko@gmail.com>
License: MIT
Classifier: License :: OSI Approved :: MIT License
License-File: LICENSE
Requires-Dist: pytest-json-report (>=1.2)
Requires-Dist: click
Requires-Dist: pyyaml
Requires-Dist: pytest
Requires-Dist: pytest-clarity
Requires-Dist: PyGitHub
Requires-Dist: six
Requires-Dist: rich
Requires-Dist: jinja2
Requires-Dist: textfsm
